<?xml version="1.0" encoding="UTF-8"?>
<r xsi:noNamespaceSchemaLocation="../../../../../gtcore/schemas/fiu-dict-schema.xsd"
   xml:lang="yrk" xmlns:xsi="http://www.w3.org/2001/XMLSchema-instance"
   xmlns:xs="http://www.w3.org/2001/XMLSchema"
   xmlns:hfp="http://www.w3.org/2001/XMLSchema-hasFacetAndProperty"
   xmlns:fn="http://www.w3.org/2005/02/xpath-functions">
  <e>
    <lg>
      <l pos="Po">ерня</l>

      <stg>
        <st Contlex="POSTP_">ерня</st>
      </stg>
    </lg>

    <mg>
      <defNative/>

      <tg xml:lang="eng">
        <t/>
      </tg>

      <tg xml:lang="est">
        <t pos="Pr">keskel</t>

        <t pos="Pr">keset</t>
      </tg>

      <tg xml:lang="fin">
        <t pos="Po">keskellä</t>
      </tg>

      <tg xml:lang="rus">
        <t/>
      </tg>
    </mg>

    <!--  -->
  </e>

  <e>
    <lg>
      <l pos="Po">едʼ</l>

      <stg>
        <st Contlex="POSTP_">едʼ</st>
      </stg>
    </lg>

    <mg>
      <defNative/>

      <tg xml:lang="eng">
        <t/>
      </tg>

      <tg xml:lang="est">
        <t/>
      </tg>

      <tg xml:lang="fin">
        <t pos="Po">kohti</t>
      </tg>

      <tg xml:lang="rus">
        <t/>
      </tg>
    </mg>

    <!--  -->
  </e>

  <e>
    <lg>
      <l pos="Po">екана</l>

      <stg>
        <st Contlex="POSTP_">екана</st>
      </stg>
    </lg>

    <mg>
      <defNative/>

      <tg xml:lang="eng">
        <t/>
      </tg>

      <tg xml:lang="est">
        <t/>
      </tg>

      <tg xml:lang="fin">
        <t pos="Po">vastapäätä</t>
      </tg>

      <tg xml:lang="rus">
        <t/>
      </tg>
    </mg>
  </e>

  <e>
    <lg>
      <l pos="Po">етʼ</l>

      <stg>
        <st Contlex="POSTP_">етʼ</st>
      </stg>
    </lg>

    <mg>
      <defNative/>

      <tg xml:lang="eng">
        <t/>
      </tg>

      <tg xml:lang="est">
        <t/>
      </tg>

      <tg xml:lang="fin">
        <t pos="Po">kohti</t>
      </tg>

      <tg xml:lang="rus">
        <t/>
      </tg>
    </mg>

    <!--  -->
  </e>

  <e>
    <lg>
      <l pos="Po">еˮня</l>

      <stg>
        <st Contlex="POSTP_">еˮня</st>
      </stg>
    </lg>

    <mg>
      <defNative/>

      <tg xml:lang="eng">
        <t/>
      </tg>

      <tg xml:lang="est">
        <t/>
      </tg>

      <tg xml:lang="fin">
        <t>kohdalla</t>

        <t>vastapäätä</t>

        <t>kautta</t>
      </tg>

      <tg xml:lang="rus">
        <t/>
      </tg>
    </mg>

    <!--  -->
  </e>

  <e>
    <lg>
      <l pos="Po">еˮэмня</l>

      <stg>
        <st Contlex="POSTP_">еˮэмня</st>
      </stg>
    </lg>

    <mg>
      <defNative/>

      <tg xml:lang="eng">
        <t/>
      </tg>

      <tg xml:lang="est">
        <t/>
      </tg>

      <tg xml:lang="fin">
        <t pos="Po">varten</t>
      </tg>

      <tg xml:lang="rus">
        <t/>
      </tg>
    </mg>

    <!--  -->
  </e>

  <e>
    <lg>
      <l pos="Po">ёльцьмана</l>

      <stg>
        <st Contlex="POSTP_">ёльцьмана</st>
      </stg>
    </lg>

    <mg>
      <defNative/>

      <tg xml:lang="eng">
        <t pos="Po">until</t>
      </tg>

      <tg xml:lang="est">
        <t pos="Po">-ni</t>
      </tg>

      <tg xml:lang="fin">
        <t pos="Po">asti</t>
      </tg>

      <tg xml:lang="rus">
        <t/>
      </tg>
    </mg>
  </e>

  <e>
    <lg>
      <l pos="Po">ёльцьӈгад</l>

      <stg>
        <st Contlex="POSTP_">ёльцьӈгад</st>
      </stg>
    </lg>

    <mg>
      <defNative/>

      <tg xml:lang="eng">
        <t pos="Po">from</t>
      </tg>

      <tg xml:lang="est">
        <t pos="Po">alates</t>
      </tg>

      <tg xml:lang="fin">
        <t pos="Po">lähtien</t>
      </tg>

      <tg xml:lang="rus">
        <t/>
      </tg>
    </mg>
  </e>

  <e>
    <lg>
      <l pos="Po">ёльцьӈгана</l>

      <stg>
        <st Contlex="POSTP_">ёльцьӈгана</st>
      </stg>
    </lg>

    <mg>
      <defNative/>

      <tg xml:lang="eng">
        <t>during</t>

        <t>at</t>
      </tg>

      <tg xml:lang="est">
        <t pos="Po">ajal</t>
      </tg>

      <tg xml:lang="fin">
        <t pos="Po">aikana</t>
      </tg>

      <tg xml:lang="rus">
        <t/>
      </tg>
    </mg>
  </e>

  <e>
    <lg>
      <l pos="Po">ёльцяндʼ</l>

      <stg>
        <st Contlex="POSTP_">ёльцяндʼ</st>
      </stg>
    </lg>

    <mg>
      <defNative/>

      <tg xml:lang="eng">
        <t/>
      </tg>

      <tg xml:lang="est">
        <t/>
      </tg>

      <tg xml:lang="fin">
        <t pos="Po">asti</t>
      </tg>

      <tg xml:lang="rus">
        <t pos="Po">до</t>
      </tg>
    </mg>
  </e>

  <e>
    <lg>
      <l pos="Po">ирмня</l>

      <stg>
        <st Contlex="POSTP_">ирмня</st>
      </stg>
    </lg>

    <mg>
      <defNative/>

      <tg xml:lang="eng">
        <t/>
      </tg>

      <tg xml:lang="est">
        <t/>
      </tg>

      <tg xml:lang="fin">
        <t>vieressä</t>

        <t>vierestä</t>

        <t>ohi</t>
      </tg>

      <tg xml:lang="rus">
        <t/>
      </tg>
    </mg>

    <!--  -->
  </e>

  <e>
    <lg>
      <l pos="Po">ирня</l>

      <stg>
        <st Contlex="POSTP_">ирня</st>
      </stg>
    </lg>

    <mg>
      <defNative/>

      <tg xml:lang="eng">
        <t/>
      </tg>

      <tg xml:lang="est">
        <t/>
      </tg>

      <tg xml:lang="fin">
        <t>vieressä</t>

        <t>vastapäätä</t>
      </tg>

      <tg xml:lang="rus">
        <t/>
      </tg>
    </mg>

    <!--  -->
  </e>

  <e>
    <lg>
      <l pos="Po">ирняд</l>

      <stg>
        <st Contlex="POSTP_">ирняд</st>
      </stg>
    </lg>

    <mg>
      <defNative/>

      <tg xml:lang="eng">
        <t/>
      </tg>

      <tg xml:lang="est">
        <t/>
      </tg>

      <tg xml:lang="fin">
        <t pos="Po">vierestä</t>
      </tg>

      <tg xml:lang="rus">
        <t/>
      </tg>
    </mg>

    <!--  -->
  </e>

  <e>
    <lg>
      <l pos="Po">мальӈгана</l>

      <stg>
        <st Contlex="POSTP_">мальӈгана</st>
      </stg>
    </lg>

    <mg>
      <defNative/>

      <tg xml:lang="eng">
        <t/>
      </tg>

      <tg xml:lang="est">
        <t/>
      </tg>

      <tg xml:lang="fin">
        <t pos="Po">aikana</t>
      </tg>

      <tg xml:lang="rus">
        <t/>
      </tg>
    </mg>

    <!--  -->
  </e>

  <e>
    <lg>
      <l pos="Po">мюʼ</l>

      <stg>
        <st Contlex="POSTP_">мюʼ</st>
      </stg>
    </lg>

    <mg>
      <defNative/>

      <tg xml:lang="eng">
        <t/>
      </tg>

      <tg xml:lang="est">
        <t/>
      </tg>

      <tg xml:lang="fin">
        <t pos="Po">sisään</t>
      </tg>

      <tg xml:lang="rus">
        <t/>
      </tg>
    </mg>

    <!--  -->
  </e>

  <e>
    <lg>
      <l pos="Po">мюд</l>

      <stg>
        <st Contlex="POSTP_">мюд</st>
      </stg>
    </lg>

    <mg>
      <defNative/>

      <tg xml:lang="eng">
        <t/>
      </tg>

      <tg xml:lang="est">
        <t/>
      </tg>

      <tg xml:lang="fin">
        <t>sisälta</t>

        <t>sisästä</t>
      </tg>

      <tg xml:lang="rus">
        <t/>
      </tg>
    </mg>

    <!--  -->
  </e>

  <e>
    <lg>
      <l pos="Po">мюмня</l>

      <stg>
        <st Contlex="POSTP_">мюмня</st>
      </stg>
    </lg>

    <mg>
      <defNative/>

      <tg xml:lang="eng">
        <t/>
      </tg>

      <tg xml:lang="est">
        <t/>
      </tg>

      <tg xml:lang="fin">
        <t pos="Po">sisäkautta</t>
      </tg>

      <tg xml:lang="rus">
        <t/>
      </tg>
    </mg>

    <!--  -->
  </e>

  <e>
    <lg>
      <l pos="Po">мюня</l>

      <stg>
        <st Contlex="POSTP_">мюня</st>
      </stg>
    </lg>

    <mg>
      <defNative/>

      <tg xml:lang="eng">
        <t/>
      </tg>

      <tg xml:lang="est">
        <t/>
      </tg>

      <tg xml:lang="fin">
        <t pos="Po">sisällä</t>
      </tg>

      <tg xml:lang="rus">
        <t/>
      </tg>
    </mg>

    <!--  -->
  </e>

  <e>
    <lg>
      <l pos="Po">мянʼ</l>

      <stg>
        <st Contlex="POSTP_">мянʼ</st>
      </stg>
    </lg>

    <mg>
      <defNative/>

      <tg xml:lang="eng">
        <t/>
      </tg>

      <tg xml:lang="est">
        <t/>
      </tg>

      <tg xml:lang="fin">
        <t pos="Po">mukaan</t>
      </tg>

      <tg xml:lang="rus">
        <t/>
      </tg>
    </mg>
  </e>

  <e>
    <lg>
      <l pos="Po">немюʼ</l>

      <stg>
        <st Contlex="POSTP_">немюʼ</st>
      </stg>
    </lg>

    <mg>
      <defNative/>

      <tg xml:lang="eng">
        <t/>
      </tg>

      <tg xml:lang="est">
        <t/>
      </tg>

      <tg xml:lang="fin">
        <t>viereen</t>

        <t>lähelle</t>
      </tg>

      <tg xml:lang="rus">
        <t/>
      </tg>
    </mg>
  </e>

  <e>
    <lg>
      <l pos="Po">нерад</l>

      <stg>
        <st Contlex="POSTP_">нерад</st>
      </stg>
    </lg>

    <mg>
      <defNative/>

      <tg xml:lang="eng">
        <t/>
      </tg>

      <tg xml:lang="est">
        <t/>
      </tg>

      <tg xml:lang="fin">
        <t pos="Po">edestä</t>
      </tg>

      <tg xml:lang="rus">
        <t/>
      </tg>
    </mg>

    <!--  -->
  </e>

  <e>
    <lg>
      <l pos="Po">нермня</l>

      <stg>
        <st Contlex="POSTP_">нермня</st>
      </stg>
    </lg>

    <mg>
      <defNative/>

      <tg xml:lang="eng">
        <t/>
      </tg>

      <tg xml:lang="est">
        <t/>
      </tg>

      <tg xml:lang="fin">
        <t pos="Po">editse</t>
      </tg>

      <tg xml:lang="rus">
        <t/>
      </tg>
    </mg>

    <!--  -->
  </e>

  <e>
    <lg>
      <l pos="Po">нерня</l>

      <stg>
        <st Contlex="POSTP_">нерня</st>
      </stg>
    </lg>

    <mg>
      <defNative/>

      <tg xml:lang="eng">
        <t/>
      </tg>

      <tg xml:lang="est">
        <t/>
      </tg>

      <tg xml:lang="fin">
        <t pos="Po">edessä</t>
      </tg>

      <tg xml:lang="rus">
        <t/>
      </tg>
    </mg>

    <!--  -->
  </e>

  <e>
    <lg>
      <l pos="Po">нерняʼ</l>

      <stg>
        <st Contlex="POSTP_">нерняʼ</st>
      </stg>
    </lg>

    <mg>
      <defNative/>

      <tg xml:lang="eng">
        <t/>
      </tg>

      <tg xml:lang="est">
        <t pos="Po">ette</t>

        <t pos="Po">edasi</t>
      </tg>

      <tg xml:lang="fin">
        <t pos="Po">eteenpäin</t>
      </tg>

      <tg xml:lang="rus">
        <t pos="Po">вперёд</t>
      </tg>
    </mg>

    <!--  -->
  </e>

  <e>
    <lg>
      <l pos="Po">нерцюна</l>

      <stg>
        <st Contlex="POSTP_">нерцюна</st>
      </stg>
    </lg>

    <mg>
      <defNative/>

      <tg xml:lang="eng">
        <t/>
      </tg>

      <tg xml:lang="est">
        <t/>
      </tg>

      <tg xml:lang="fin">
        <t pos="Po">edellä</t>
      </tg>

      <tg xml:lang="rus">
        <t/>
      </tg>
    </mg>

    <!--  -->
  </e>

  <e>
    <lg>
      <l pos="Po">нерцюмня</l>

      <stg>
        <st Contlex="POSTP_">нерцюмня</st>
      </stg>
    </lg>

    <mg>
      <defNative/>

      <tg xml:lang="eng">
        <t/>
      </tg>

      <tg xml:lang="est">
        <t/>
      </tg>

      <tg xml:lang="fin">
        <t pos="Po">editse</t>
      </tg>

      <tg xml:lang="rus">
        <t/>
      </tg>
    </mg>

    <!--  -->
  </e>

  <e>
    <lg>
      <l pos="Po">нерцюʼ</l>

      <stg>
        <st Contlex="POSTP_">нерцюʼ</st>
      </stg>
    </lg>

    <mg>
      <defNative/>

      <tg xml:lang="eng">
        <t/>
      </tg>

      <tg xml:lang="est">
        <t/>
      </tg>

      <tg xml:lang="fin">
        <t pos="Po">ennen</t>
      </tg>

      <tg xml:lang="rus">
        <t/>
      </tg>
    </mg>

    <!--  -->
  </e>

  <e>
    <lg>
      <l pos="Po">нерʼ</l>

      <stg>
        <st Contlex="POSTP_">нерʼ</st>
      </stg>
    </lg>

    <mg>
      <defNative/>

      <tg xml:lang="eng">
        <t/>
      </tg>

      <tg xml:lang="est">
        <t/>
      </tg>

      <tg xml:lang="fin">
        <t pos="Po">eteen</t>
      </tg>

      <tg xml:lang="rus">
        <t/>
      </tg>
    </mg>

    <!--  -->
  </e>

  <e>
    <lg>
      <l pos="Po">нид</l>

      <stg>
        <st Contlex="POSTP_">нид</st>
      </stg>
    </lg>

    <mg>
      <defNative/>

      <tg xml:lang="eng">
        <t/>
      </tg>

      <tg xml:lang="est">
        <t/>
      </tg>

      <tg xml:lang="fin">
        <t>päältä</t>

        <t>syystä</t>

        <t>takia</t>
      </tg>

      <tg xml:lang="rus">
        <t/>
      </tg>
    </mg>

    <!--  -->
  </e>

  <e>
    <lg>
      <l pos="Po">нимня</l>

      <stg>
        <st Contlex="POSTP_">нимня</st>
      </stg>
    </lg>

    <mg>
      <defNative/>

      <tg xml:lang="eng">
        <t/>
      </tg>

      <tg xml:lang="est">
        <t/>
      </tg>

      <tg xml:lang="fin">
        <t pos="Po">kautta</t>

        <t pos="Po">pitkin</t>

        <t pos="Po">yli</t>
      </tg>

      <tg xml:lang="rus">
        <t/>
      </tg>
    </mg>

    <!--  -->
  </e>

  <e>
    <lg>
      <l pos="Po">ниня</l>

      <stg>
        <st Contlex="POSTP_">ниня</st>
      </stg>
    </lg>

    <mg>
      <defNative/>

      <tg xml:lang="eng">
        <t/>
      </tg>

      <tg xml:lang="est">
        <t/>
      </tg>

      <tg xml:lang="fin">
        <t pos="Po">päällä</t>
      </tg>

      <tg xml:lang="rus">
        <t/>
      </tg>
    </mg>

    <!--  -->
  </e>

  <e>
    <lg>
      <l pos="Po">ни</l>

      <stg>
        <st Contlex="POSTP_">ниʼ</st>
      </stg>
    </lg>

    <mg>
      <defNative/>

      <tg xml:lang="eng">
        <t/>
      </tg>

      <tg xml:lang="est">
        <t/>
      </tg>

      <tg xml:lang="fin">
        <t pos="Po">päälle</t>
      </tg>

      <tg xml:lang="rus">
        <t/>
      </tg>
    </mg>

    <!--  -->
  </e>

  <e>
    <lg>
      <l pos="Po">няʼ</l>

      <stg>
        <st Contlex="POSTP_">няʼ</st>
      </stg>
    </lg>

    <mg>
      <defNative/>

      <tg xml:lang="eng">
        <t/>
      </tg>

      <tg xml:lang="est">
        <t/>
      </tg>

      <tg xml:lang="fin">
        <t>luo</t>

        <t>luokse</t>
      </tg>

      <tg xml:lang="rus">
        <t/>
      </tg>
    </mg>

    <!--  -->
  </e>

  <e>
    <lg>
      <l pos="Po">няд</l>

      <stg>
        <st Contlex="POSTP_">няд</st>
      </stg>
    </lg>

    <mg>
      <defNative/>

      <tg xml:lang="eng">
        <t/>
      </tg>

      <tg xml:lang="est">
        <t/>
      </tg>

      <tg xml:lang="fin">
        <t pos="Po">luota</t>
      </tg>

      <tg xml:lang="rus">
        <t/>
      </tg>
    </mg>

    <!--  -->
  </e>

  <e>
    <lg>
      <l pos="Po">някуʼ</l>

      <stg>
        <st Contlex="POSTP_">някуʼ</st>
      </stg>
    </lg>

    <mg>
      <defNative/>

      <tg xml:lang="eng">
        <t/>
      </tg>

      <tg xml:lang="est">
        <t/>
      </tg>

      <tg xml:lang="fin">
        <t>luo</t>

        <t>luokse</t>
      </tg>

      <tg xml:lang="rus">
        <t/>
      </tg>
    </mg>

    <!--  -->
  </e>

  <e>
    <lg>
      <l pos="Po">някуд</l>

      <stg>
        <st Contlex="POSTP_">някуд</st>
      </stg>
    </lg>

    <mg>
      <defNative/>

      <tg xml:lang="eng">
        <t/>
      </tg>

      <tg xml:lang="est">
        <t/>
      </tg>

      <tg xml:lang="fin">
        <t pos="Po">luota</t>
      </tg>

      <tg xml:lang="rus">
        <t/>
      </tg>
    </mg>

    <!--  -->
  </e>

  <e>
    <lg>
      <l pos="Po">някумна</l>

      <stg>
        <st Contlex="POSTP_">някумна</st>
      </stg>
    </lg>

    <mg>
      <defNative/>

      <tg xml:lang="eng">
        <t/>
      </tg>

      <tg xml:lang="est">
        <t/>
      </tg>

      <tg xml:lang="fin">
        <t pos="Po">kautta</t>
      </tg>

      <tg xml:lang="rus">
        <t/>
      </tg>
    </mg>

    <!--  -->
  </e>

  <e>
    <lg>
      <l pos="Po">някуна</l>

      <stg>
        <st Contlex="POSTP_">някуна</st>
      </stg>
    </lg>

    <mg>
      <defNative/>

      <tg xml:lang="eng">
        <t/>
      </tg>

      <tg xml:lang="est">
        <t/>
      </tg>

      <tg xml:lang="fin">
        <t pos="Po">luona</t>
      </tg>

      <tg xml:lang="rus">
        <t/>
      </tg>
    </mg>

    <!--  -->
  </e>

  <e>
    <lg>
      <l pos="Po">нямна</l>

      <stg>
        <st Contlex="POSTP_">нямна</st>
      </stg>
    </lg>

    <mg>
      <defNative/>

      <tg xml:lang="eng">
        <t/>
      </tg>

      <tg xml:lang="est">
        <t/>
      </tg>

      <tg xml:lang="fin">
        <t pos="Po">kautta</t>
      </tg>

      <tg xml:lang="rus">
        <t/>
      </tg>
    </mg>

    <!--  -->
  </e>

  <e>
    <lg>
      <l pos="Po">няна</l>

      <stg>
        <st Contlex="POSTP_">няна</st>
      </stg>
    </lg>

    <mg>
      <defNative/>

      <tg xml:lang="eng">
        <t/>
      </tg>

      <tg xml:lang="est">
        <t/>
      </tg>

      <tg xml:lang="fin">
        <t pos="Po">luona</t>
      </tg>

      <tg xml:lang="rus">
        <t/>
      </tg>
    </mg>

    <!--  -->
  </e>

  <e>
    <lg>
      <l pos="Po">нярпойʼ</l>

      <stg>
        <st Contlex="POSTP_">нярпойʼ</st>
      </stg>
    </lg>

    <mg>
      <defNative/>

      <tg xml:lang="eng">
        <t/>
      </tg>

      <tg xml:lang="fin">
        <t>poikki</t>

        <t>poikittain</t>
      </tg>

      <tg xml:lang="rus">
        <t/>
      </tg>
    </mg>
  </e>

  <e>
    <lg>
      <l pos="Po">няюд</l>

      <stg>
        <st Contlex="POSTP_">няюд</st>
      </stg>
    </lg>

    <mg>
      <defNative/>

      <tg xml:lang="eng">
        <t/>
      </tg>

      <tg xml:lang="est">
        <t/>
      </tg>

      <tg xml:lang="fin">
        <t pos="Po">suunnasta</t>
      </tg>

      <tg xml:lang="rus">
        <t/>
      </tg>
    </mg>

    <!--  -->
  </e>

  <e>
    <lg>
      <l pos="Po">няюмна</l>

      <stg>
        <st Contlex="POSTP_">няюмна</st>
      </stg>
    </lg>

    <mg>
      <defNative/>

      <tg xml:lang="eng">
        <t/>
      </tg>

      <tg xml:lang="est">
        <t/>
      </tg>

      <tg xml:lang="fin">
        <t pos="Po">kautta</t>
      </tg>

      <tg xml:lang="rus">
        <t/>
      </tg>
    </mg>

    <!--  -->
  </e>

  <e>
    <lg>
      <l pos="Po">няюна</l>

      <stg>
        <st Contlex="POSTP_">няюна</st>
      </stg>
    </lg>

    <mg>
      <defNative/>

      <tg xml:lang="eng">
        <t/>
      </tg>

      <tg xml:lang="est">
        <t/>
      </tg>

      <tg xml:lang="fin">
        <t pos="Po">suunnassa</t>
      </tg>

      <tg xml:lang="rus">
        <t/>
      </tg>
    </mg>

    <!--  -->
  </e>

  <e>
    <lg>
      <l pos="Po">няюʼ</l>

      <stg>
        <st Contlex="POSTP_">няюʼ</st>
      </stg>
    </lg>

    <mg>
      <defNative/>

      <tg xml:lang="eng">
        <t/>
      </tg>

      <tg xml:lang="est">
        <t/>
      </tg>

      <tg xml:lang="fin">
        <t>suuntaan</t>

        <t>päin</t>
      </tg>

      <tg xml:lang="rus">
        <t/>
      </tg>
    </mg>

    <!--  -->
  </e>

  <e>
    <lg>
      <l pos="Po">ӈылад</l>

      <stg>
        <st Contlex="POSTP_">ӈылад</st>
      </stg>
    </lg>

    <mg>
      <defNative/>

      <tg xml:lang="eng">
        <t/>
      </tg>

      <tg xml:lang="est">
        <t/>
      </tg>

      <tg xml:lang="fin">
        <t pos="Po">alta</t>
      </tg>

      <tg xml:lang="rus">
        <t/>
      </tg>
    </mg>

    <!--  -->
  </e>

  <e>
    <lg>
      <l pos="Po">ӈылмна</l>

      <stg>
        <st Contlex="POSTP_">ӈылмна</st>
      </stg>
    </lg>

    <mg>
      <defNative/>

      <tg xml:lang="eng">
        <t pos="Po">under</t>
      </tg>

      <tg xml:lang="est">
        <t pos="Po">all</t>
      </tg>

      <tg xml:lang="fin">
        <t pos="Po">alla</t>
      </tg>

      <tg xml:lang="rus">
        <t pos="Po">под</t>
      </tg>
    </mg>

    <!--  -->
  </e>

  <e>
    <lg>
      <l pos="Po">ӈылна</l>

      <stg>
        <st Contlex="POSTP_">ӈылна</st>
      </stg>
    </lg>

    <mg>
      <defNative/>

      <tg xml:lang="eng">
        <t/>
      </tg>

      <tg xml:lang="est">
        <t/>
      </tg>

      <tg xml:lang="fin">
        <t pos="Po">alla</t>
      </tg>

      <tg xml:lang="rus">
        <t/>
      </tg>
    </mg>

    <!--  -->
  </e>

  <e>
    <lg>
      <l pos="Po">ӈылʼ</l>

      <stg>
        <st Contlex="POSTP_">ӈылʼ</st>
      </stg>
    </lg>

    <mg>
      <defNative/>

      <tg xml:lang="eng">
        <t/>
      </tg>

      <tg xml:lang="est">
        <t/>
      </tg>

      <tg xml:lang="fin">
        <t pos="Po">alle</t>
      </tg>

      <tg xml:lang="rus">
        <t/>
      </tg>
    </mg>

    <!--  -->
  </e>

  <e>
    <lg>
      <l pos="Po">ӈэломана</l>

      <stg>
        <st Contlex="POSTP_">ӈэломана</st>
      </stg>
    </lg>

    <mg>
      <defNative/>

      <tg xml:lang="eng">
        <t/>
      </tg>

      <tg xml:lang="est">
        <t/>
      </tg>

      <tg xml:lang="fin">
        <t>sijasta</t>

        <t>lisäksi</t>

        <t>paitsi</t>
      </tg>

      <tg xml:lang="rus">
        <t/>
      </tg>
    </mg>

    <!--  -->
  </e>

  <e>
    <lg>
      <l pos="Po">ӈэсондʼ</l>

      <stg>
        <st Contlex="POSTP_">ӈэсондʼ</st>
      </stg>
    </lg>

    <mg>
      <defNative/>

      <tg xml:lang="eng">
        <t/>
      </tg>

      <tg xml:lang="est">
        <t/>
      </tg>

      <tg xml:lang="fin">
        <t>asti</t>

        <t>saakka</t>
      </tg>

      <tg xml:lang="rus">
        <t/>
      </tg>
    </mg>

    <!--  -->
  </e>

  <e>
    <lg>
      <l pos="Po">пуд</l>

      <stg>
        <st Contlex="POSTP_">пуд</st>
      </stg>
    </lg>

    <mg>
      <defNative/>

      <tg xml:lang="eng">
        <t/>
      </tg>

      <tg xml:lang="est">
        <t/>
      </tg>

      <tg xml:lang="fin">
        <t pos="Po">jäljestä</t>
      </tg>

      <tg xml:lang="rus">
        <t/>
      </tg>
    </mg>

    <!--  -->
  </e>

  <e>
    <lg>
      <l pos="Po">пумна</l>

      <stg>
        <st Contlex="POSTP_">пумна</st>
      </stg>
    </lg>

    <mg>
      <defNative/>

      <tg xml:lang="eng">
        <t/>
      </tg>

      <tg xml:lang="est">
        <t/>
      </tg>

      <tg xml:lang="fin">
        <t>jälkeen</t>

        <t>perään</t>
      </tg>

      <tg xml:lang="rus">
        <t/>
      </tg>
    </mg>

    <!--  -->
  </e>

  <e>
    <lg>
      <l pos="Po">пуна</l>

      <stg>
        <st Contlex="POSTP_">пуна</st>
      </stg>
    </lg>

    <mg>
      <defNative/>

      <tg xml:lang="eng">
        <t/>
      </tg>

      <tg xml:lang="est">
        <t/>
      </tg>

      <tg xml:lang="fin">
        <t pos="Po">jäljessä</t>
      </tg>

      <tg xml:lang="rus">
        <t/>
      </tg>
    </mg>

    <!--  -->
  </e>

  <e>
    <lg>
      <l pos="Po">пуняд</l>

      <stg>
        <st Contlex="POSTP_">пуняд</st>
      </stg>
    </lg>

    <mg>
      <defNative/>

      <tg xml:lang="eng">
        <t/>
      </tg>

      <tg xml:lang="est">
        <t/>
      </tg>

      <tg xml:lang="fin">
        <t pos="Po">takaa</t>
      </tg>

      <tg xml:lang="rus">
        <t/>
      </tg>
    </mg>

    <!--  -->
  </e>

  <e>
    <lg>
      <l pos="Po">пунямна</l>

      <stg>
        <st Contlex="POSTP_">пунямна</st>
      </stg>
    </lg>

    <mg>
      <defNative/>

      <tg xml:lang="eng">
        <t/>
      </tg>

      <tg xml:lang="est">
        <t/>
      </tg>

      <tg xml:lang="fin">
        <t pos="Po">takana</t>
      </tg>

      <tg xml:lang="rus">
        <t/>
      </tg>
    </mg>

    <!--  -->
  </e>

  <e>
    <lg>
      <l pos="Po">пуняна</l>

      <stg>
        <st Contlex="POSTP_">пуняна</st>
      </stg>
    </lg>

    <mg>
      <defNative/>

      <tg xml:lang="eng">
        <t/>
      </tg>

      <tg xml:lang="est">
        <t/>
      </tg>

      <tg xml:lang="fin">
        <t pos="Po">takana</t>
      </tg>

      <tg xml:lang="rus">
        <t/>
      </tg>
    </mg>

    <!--  -->
  </e>

  <e>
    <lg>
      <l pos="Po">пуняʼ</l>

      <stg>
        <st Contlex="POSTP_">пуняʼ</st>
      </stg>
    </lg>

    <mg>
      <defNative/>

      <tg xml:lang="eng">
        <t/>
      </tg>

      <tg xml:lang="est">
        <t/>
      </tg>

      <tg xml:lang="fin">
        <t>takaisin</t>

        <t>taakse</t>
      </tg>

      <tg xml:lang="rus">
        <t/>
      </tg>
    </mg>

    <!--  -->
  </e>

  <e>
    <lg>
      <l pos="Po">пуʼ</l>

      <stg>
        <st Contlex="POSTP_">пуʼ</st>
      </stg>
    </lg>

    <mg>
      <defNative/>

      <tg xml:lang="eng">
        <t/>
      </tg>

      <tg xml:lang="est">
        <t/>
      </tg>

      <tg xml:lang="fin">
        <t pos="Po">jälkeen</t>
      </tg>

      <tg xml:lang="rus">
        <t/>
      </tg>
    </mg>

    <!--  -->
  </e>

  <e>
    <lg>
      <l pos="Po">серевʼ</l>

      <stg>
        <st Contlex="POSTP_">серевʼ</st>
      </stg>
    </lg>

    <mg>
      <defNative/>

      <tg xml:lang="eng">
        <t/>
      </tg>

      <tg xml:lang="est">
        <t/>
      </tg>

      <tg xml:lang="fin">
        <t>mukaisesti</t>

        <t>tavalla</t>
      </tg>

      <tg xml:lang="rus">
        <t/>
      </tg>
    </mg>

    <!--  -->
  </e>

  <e>
    <lg>
      <l pos="Po">сермня</l>

      <stg>
        <st Contlex="POSTP_">сермня</st>
      </stg>
    </lg>

    <mg>
      <defNative/>

      <tg xml:lang="eng">
        <t/>
      </tg>

      <tg xml:lang="est">
        <t pos="Po">kohta, -st</t>
      </tg>

      <tg xml:lang="fin">
        <t>aiheesta</t>

        <t>liittyen</t>
      </tg>

      <tg xml:lang="rus">
        <t/>
      </tg>
    </mg>

    <!--  -->
  </e>

  <e>
    <lg>
      <l pos="Po">сертревʼ</l>

      <stg>
        <st Contlex="POSTP_">сертревʼ</st>
      </stg>
    </lg>

    <mg>
      <defNative/>

      <tg xml:lang="eng">
        <t/>
      </tg>

      <tg xml:lang="est">
        <t/>
      </tg>

      <tg xml:lang="fin">
        <t pos="Po">mukaan</t>
      </tg>

      <tg xml:lang="rus">
        <t/>
      </tg>
    </mg>

    <!--  -->
  </e>

  <e>
    <lg>
      <l pos="Po">серʼ</l>

      <stg>
        <st Contlex="POSTP_">серʼ</st>
      </stg>
    </lg>

    <mg>
      <defNative/>

      <tg xml:lang="eng">
        <t/>
      </tg>

      <tg xml:lang="est">
        <t/>
      </tg>

      <tg xml:lang="fin">
        <t pos="Po">tavalla</t>
      </tg>

      <tg xml:lang="rus">
        <t/>
      </tg>
    </mg>

    <!--  -->
  </e>

  <e>
    <lg>
      <l pos="Po">тавна</l>

      <stg>
        <st Contlex="POSTP_">тавна</st>
      </stg>
    </lg>

    <mg>
      <defNative/>

      <tg xml:lang="eng">
        <t/>
      </tg>

      <tg xml:lang="est">
        <t/>
      </tg>

      <tg xml:lang="fin">
        <t>kautta</t>

        <t>koko</t>
      </tg>

      <tg xml:lang="rus">
        <t/>
      </tg>
    </mg>
  </e>

  <e>
    <lg>
      <l pos="Po">тяхад</l>

      <stg>
        <st Contlex="POSTP_">тяхад</st>
      </stg>
    </lg>

    <mg>
      <defNative/>

      <tg xml:lang="eng">
        <t/>
      </tg>

      <tg xml:lang="est">
        <t/>
      </tg>

      <tg xml:lang="fin">
        <t pos="Po">takaa</t>
      </tg>

      <tg xml:lang="rus">
        <t/>
      </tg>
    </mg>

    <!--  -->
  </e>

  <e>
    <lg>
      <l pos="Po">тяхакуна</l>

      <stg>
        <st Contlex="POSTP_">тяхакуна</st>
      </stg>
    </lg>

    <mg>
      <defNative/>

      <tg xml:lang="eng">
        <t/>
      </tg>

      <tg xml:lang="est">
        <t/>
      </tg>

      <tg xml:lang="fin">
        <t>aiemmin</t>

        <t>kauemmin</t>
      </tg>

      <tg xml:lang="rus">
        <t/>
      </tg>
    </mg>

    <!--  -->
  </e>

  <e>
    <lg>
      <l pos="Po">тяхакуʼ</l>

      <stg>
        <st Contlex="POSTP_">тяхакуʼ</st>
      </stg>
    </lg>

    <mg>
      <defNative/>

      <tg xml:lang="eng">
        <t/>
      </tg>

      <tg xml:lang="est">
        <t/>
      </tg>

      <tg xml:lang="fin">
        <t>aiemmas</t>

        <t>kauemmas</t>
      </tg>

      <tg xml:lang="rus">
        <t/>
      </tg>
    </mg>

    <!--  -->
  </e>

  <e>
    <lg>
      <l pos="Po">тахамана</l>

      <stg>
        <st Contlex="POSTP_">тахамана</st>
      </stg>
    </lg>

    <mg>
      <defNative/>

      <tg xml:lang="eng">
        <t>through</t>
      </tg>

      <tg xml:lang="est">
        <t>läbi</t>
      </tg>

      <tg xml:lang="fin">
        <t>läpi</t>

        <t>lävitse</t>
      </tg>

      <tg xml:lang="rus">
        <t>сквозь</t>
      </tg>
    </mg>

    <!--  -->
  </e>

  <e>
    <lg>
      <l pos="Po">тяхана</l>

      <stg>
        <st Contlex="POSTP_">тяхана</st>
      </stg>
    </lg>

    <mg>
      <defNative/>

      <tg xml:lang="eng">
        <t>behind</t>
      </tg>

      <tg xml:lang="est">
        <t>taga</t>
      </tg>

      <tg xml:lang="fin">
        <t pos="Po">takana</t>
      </tg>

      <tg xml:lang="rus">
        <t/>
      </tg>
    </mg>

    <!--  -->
  </e>

  <e>
    <lg>
      <l pos="Po">тяхаʼ</l>

      <stg>
        <st Contlex="POSTP_">тяхаʼ</st>
      </stg>
    </lg>

    <mg>
      <defNative/>

      <tg xml:lang="eng">
        <t>behind</t>
      </tg>

      <tg xml:lang="est">
        <t>taha</t>
      </tg>

      <tg xml:lang="fin">
        <t pos="Po">taakse</t>
      </tg>

      <tg xml:lang="rus">
        <t/>
      </tg>
    </mg>

    <!--  -->
  </e>

  <e>
    <lg>
      <l pos="Po">хавна</l>

      <stg>
        <st Contlex="POSTP_">хавна</st>
      </stg>
    </lg>

    <mg>
      <defNative/>

      <tg xml:lang="eng">
        <t>except</t>
      </tg>

      <tg xml:lang="est">
        <t/>
      </tg>

      <tg xml:lang="fin">
        <t pos="Po">paitsi</t>
      </tg>

      <tg xml:lang="rus">
        <t/>
      </tg>
    </mg>

    <!--  -->
  </e>

  <e>
    <lg>
      <l pos="Po">хунзерʼ</l>

      <stg>
        <st Contlex="POSTP_">хунзерʼ</st>
      </stg>
    </lg>

    <mg>
      <defNative/>

      <tg xml:lang="eng">
        <t pos="Po">along</t>
      </tg>

      <tg xml:lang="est">
        <t pos="Po">piki</t>
      </tg>

      <tg xml:lang="fin">
        <t>myöten</t>

        <t>pitkin</t>
      </tg>

      <tg xml:lang="rus">
        <t pos="Po">вдоль</t>
      </tg>
    </mg>

    <!--  -->
  </e>

  <e>
    <lg>
      <l pos="Po">хэвувна</l>

      <stg>
        <st Contlex="POSTP_">хэвувна</st>
      </stg>
    </lg>

    <mg>
      <defNative/>

      <tg xml:lang="eng">
        <t pos="Po">along</t>
      </tg>

      <tg xml:lang="est">
        <t pos="Po">mööda</t>
      </tg>

      <tg xml:lang="fin">
        <t>ohi</t>

        <t>pitkin</t>
      </tg>

      <tg xml:lang="rus">
        <t pos="Po">мимо</t>
      </tg>
    </mg>

    <!--  -->
  </e>

  <e>
    <lg>
      <l pos="Po">хэвхана</l>

      <stg>
        <st Contlex="POSTP_">хэвхана</st>
      </stg>
    </lg>

    <mg>
      <defNative/>

      <tg xml:lang="eng">
        <t/>
      </tg>

      <tg xml:lang="est">
        <t>kõrval</t>
      </tg>

      <tg xml:lang="fin">
        <t pos="Po">viereessä</t>
      </tg>

      <tg xml:lang="rus">
        <t/>
      </tg>
    </mg>

    <!--  -->
  </e>

  <e>
    <lg>
      <l pos="Po">ядувана</l>

      <stg>
        <st Contlex="POSTP_">ядувана</st>
      </stg>
    </lg>

    <mg>
      <defNative/>

      <tg xml:lang="eng">
        <t pos="Po">beside</t>
      </tg>

      <tg xml:lang="est">
        <t pos="Po">ääres</t>
      </tg>

      <tg xml:lang="fin">
        <t>lähellä</t>

        <t>viereessä</t>
      </tg>

      <tg xml:lang="rus">
        <t>около</t>

        <t>возле</t>
      </tg>

      <!--Burkova2010:170  -->
    </mg>
  </e>

  <e>
    <lg>
      <l pos="Po">ямбанʼ</l>

      <stg>
        <st Contlex="POSTP_">ямбанʼ</st>
      </stg>
    </lg>

    <mg>
      <defNative/>

      <tg xml:lang="eng">
        <t/>
      </tg>

      <tg xml:lang="est">
        <t/>
      </tg>

      <tg xml:lang="fin">
        <t>aikana</t>

        <t>pitkin</t>
      </tg>

      <tg xml:lang="rus">
        <t/>
      </tg>
    </mg>

    <!--  -->
  </e>

  <e>
    <lg>
      <l pos="Po">ямбахана</l>

      <stg>
        <st Contlex="POSTP_">ямбахана</st>
      </stg>
    </lg>

    <mg>
      <defNative/>

      <tg xml:lang="fin">
        <t>aikana</t>

        <t>kuluessa</t>
      </tg>

      <tg xml:lang="rus">
        <t pos="Po">в продолжение</t>
      </tg>
    </mg>
  </e>
</r>
